gs_divergence/__init__.py
gs_divergence/alpha_geodesic.py
gs_divergence/geodesical_skew_divergence.py
gs_divergence/symmetrized_geodesical_skew_divergence.py
tests/__init__.py
tests/test_alpha_geodesic.py
tests/test_gs_div.py
gs_divergence-1.0.8.dist-info/LICENSE
gs_divergence-1.0.8.dist-info/METADATA
gs_divergence-1.0.8.dist-info/WHEEL
gs_divergence-1.0.8.dist-info/top_level.txt
gs_divergence-1.0.8.dist-info/RECORD
