Metadata-Version: 2.1
Name: gs-divergence
Version: 1.0.8
Summary: PyTorch implementation of α-geodesical skew divergence
Home-page: https://github.com/nocotan/geodesical_skew_divergence
Author: Masanari Kimura
Author-email: mkimura@klis.tsukuba.ac.jp
License: UNKNOWN
Platform: UNKNOWN
Requires-Dist: torch
